scrapy_tls_client/__init__.py
scrapy_tls_client/__version__.py
scrapy_tls_client/downloaderMiddleware.py
scrapy_tls_client/settings.py
scrapy_tls_client-0.0.5.dist-info/LICENSE
scrapy_tls_client-0.0.5.dist-info/METADATA
scrapy_tls_client-0.0.5.dist-info/WHEEL
scrapy_tls_client-0.0.5.dist-info/top_level.txt
scrapy_tls_client-0.0.5.dist-info/RECORD
